oemof/solph/__init__.py
oemof/solph/_console_scripts.py
oemof/solph/_energy_system.py
oemof/solph/_groupings.py
oemof/solph/_helpers.py
oemof/solph/_models.py
oemof/solph/_options.py
oemof/solph/_plumbing.py
oemof/solph/_results.py
oemof/solph/helpers.py
oemof/solph/processing.py
oemof/solph/views.py
oemof/solph/buses/__init__.py
oemof/solph/buses/_bus.py
oemof/solph/components/__init__.py
oemof/solph/components/_converter.py
oemof/solph/components/_extraction_turbine_chp.py
oemof/solph/components/_generic_chp.py
oemof/solph/components/_generic_storage.py
oemof/solph/components/_link.py
oemof/solph/components/_offset_converter.py
oemof/solph/components/_sink.py
oemof/solph/components/_source.py
oemof/solph/components/experimental/__init__.py
oemof/solph/components/experimental/_generic_caes.py
oemof/solph/components/experimental/_piecewise_linear_converter.py
oemof/solph/constraints/__init__.py
oemof/solph/constraints/equate_flows.py
oemof/solph/constraints/equate_variables.py
oemof/solph/constraints/flow_count_limit.py
oemof/solph/constraints/integral_limit.py
oemof/solph/constraints/investment_limit.py
oemof/solph/constraints/shared_limit.py
oemof/solph/constraints/storage_level.py
oemof/solph/flows/__init__.py
oemof/solph/flows/_flow.py
oemof/solph/flows/_invest_non_convex_flow_block.py
oemof/solph/flows/_investment_flow_block.py
oemof/solph/flows/_non_convex_flow_block.py
oemof/solph/flows/_shared.py
oemof/solph/flows/_simple_flow_block.py
oemof_solph-0.6.2.dist-info/entry_points.txt
oemof_solph-0.6.2.dist-info/licenses/LICENSE
oemof_solph-0.6.2.dist-info/WHEEL
oemof_solph-0.6.2.dist-info/METADATA
oemof_solph-0.6.2.dist-info/RECORD
