Metadata-Version: 2.1
Name: oemof.solph
Version: 0.5.3a1
Summary: A model generator for energy system modelling and optimisation.
Home-page: https://oemof.org
Author: oemof developer group
Author-email: contact@oemof.org
License: MIT
Project-URL: Documentation, https://oemof-solph.readthedocs.io/
Project-URL: Changelog, https://oemof-solph.readthedocs.io/en/latest/changelog.html
Project-URL: Issue Tracker, https://github.com/oemof/oemof-solph/issues
Classifier: Development Status :: 5 - Production/Stable
Classifier: Intended Audience :: Developers
Classifier: Intended Audience :: Science/Research
Classifier: License :: OSI Approved :: MIT License
Classifier: Operating System :: Unix
Classifier: Operating System :: POSIX
Classifier: Operating System :: Microsoft :: Windows
Classifier: Operating System :: MacOS
Classifier: Operating System :: OS Independent
Classifier: Programming Language :: Python
Classifier: Programming Language :: Python :: 3
Classifier: Programming Language :: Python :: 3.8
Classifier: Programming Language :: Python :: 3.9
Classifier: Programming Language :: Python :: 3.10
Classifier: Programming Language :: Python :: Implementation :: CPython
Classifier: Topic :: Utilities
Requires-Python: >=3.8
License-File: LICENSE
License-File: AUTHORS.rst
Requires-Dist: blinker
Requires-Dist: dill
Requires-Dist: numpy
Requires-Dist: pandas>=1.5.3
Requires-Dist: pyomo<7.0,>=6.6.0
Requires-Dist: networkx
Requires-Dist: oemof.tools>=0.4.2
Requires-Dist: oemof.network>=0.5.0
Provides-Extra: dev
Requires-Dist: matplotlib; extra == "dev"
Requires-Dist: nbformat; extra == "dev"
Requires-Dist: pytest; extra == "dev"
Requires-Dist: sphinx; extra == "dev"
Requires-Dist: sphinx_rtd_theme; extra == "dev"
Requires-Dist: sphinx-copybutton; extra == "dev"
Requires-Dist: sphinx-design; extra == "dev"
Requires-Dist: termcolor; extra == "dev"
Provides-Extra: examples
Requires-Dist: matplotlib; extra == "examples"
Provides-Extra: dummy
Requires-Dist: oemof; extra == "dummy"
